CHANGES.rst
MANIFEST.in
README.rst
setup.cfg
setup.py
src/cid/__init__.py
src/cid/data.csv
src/cid.egg-info/PKG-INFO
src/cid.egg-info/SOURCES.txt
src/cid.egg-info/dependency_links.txt
src/cid.egg-info/top_level.txt