Metadata-Version: 1.1
Name: cid
Version: 0.1.2
Summary: Extract Chinese identity card info (gender, birthday           and regions)
Home-page: https://github.com/lxneng/cid
Author: Eric Lo
Author-email: lxneng@gmail.com
License: BSD
Keywords: chinese-identity
Platform: UNKNOWN
Classifier: Intended Audience :: Developers
Classifier: License :: OSI Approved :: BSD License
Classifier: Operating System :: OS Independent
Classifier: Programming Language :: Python :: 2
Classifier: Programming Language :: Python :: 2.6
Classifier: Programming Language :: Python :: 2.7
Classifier: Programming Language :: Python :: 3
Classifier: Programming Language :: Python :: 3.3
Classifier: Programming Language :: Python :: 3.4
Classifier: Programming Language :: Python :: 3.5
Classifier: Programming Language :: Python :: 3.6
Classifier: Topic :: Software Development :: Libraries :: Python Modules
